Workbook

Sheet Legend
A1: Restaurant Sales Trend & Financial Model - SAMPLE DATA (synthetic)
A3: Purpose | B3: Quantify a late-summer sales decline (May 1 - Oct 7, 2026) and estimate profit under editable cost assumptions.
A4: Data source | B4: SYNTHETIC sample data in the same format as a POS 'Sales by day' export. No real business data is included in this repository.
A5: Blue text | B5: Hardcoded input or raw POS data.
A6: Black text | B6: Formula - do not overwrite.
A7: Yellow fill | B7: Key assumption you should edit. COST INPUTS ARE PLACEHOLDERS until the owners supply real figures.
A8: Tabs | B8: Assumptions > Daily (raw) > Weekly > Decomposition (orders vs. avg check, day of week) > Scenario > Monthly P&L (estimate).
A9: Important | B9: Revenue-based findings (Weekly, Decomposition) use real POS data only. Anything involving cost (Scenario profit, Monthly P&L) depends on placeholder inputs.

Sheet Assumptions
A1: Assumptions
A3: Comparison periods (week-start dates, Mondays)
A4: Base period - first week start | B4: 46146 | C4: First full Mon-Sun week of data
A5: Base period - last week start | B5: 46258 | C5: Week of Aug 24-30; late summer peak weeks included
A6: Recent period - first week start | B6: 46272 | C6: Aug 31-Sep 6 (Labor Day week) left out of both periods
A7: Recent period - last week start | B7: 46293 | C7: Last full week of data (Sep 28 - Oct 4)
A8: Base period - last day | B8: =B5+6 -> 46264 | C8: Formula
A9: Recent period - last day | B9: =B7+6 -> 46299 | C9: Formula
A11: Cost assumptions (PLACEHOLDERS - replace with owner figures)
A12: Food & beverage cost (% of net sales) | B12: 0.3 | C12: PLACEHOLDER. Typical full-service range is roughly 28-35%; owners' actual figure needed.
A13: Labor cost (% of net sales) | B13: 0.3 | C13: PLACEHOLDER. Owners' payroll figures needed.
A14: Other operating costs (% of net sales) | B14: 0.1 | C14: PLACEHOLDER. Supplies, utilities, processing fees, etc.
A15: Rent & fixed costs per month ($) | B15: 8000 | C15: PLACEHOLDER. Owners' actual figure needed.
A17: Scenario lever
A18: Share of lost weeknight sales recovered | B18: 0.25 | C18: Illustrative lever for the Scenario tab (not a forecast).

Sheet Daily
A1: Date | B1: Day of week | C1: Week start (Mon) | D1: Net sales ($) | E1: Orders | F1: Guests | G1: Avg check ($)
A2: 46143 | B2: =TEXT(A2,"dddd") -> Friday | C2: =A2-WEEKDAY(A2,2)+1 -> 46139 | D2: 1387.51 | E2: 33 | F2: 51 | G2: =IF(E2=0,0,D2/E2) -> 42.045758
A3: 46144 | B3: =TEXT(A3,"dddd") -> Saturday | C3: =A3-WEEKDAY(A3,2)+1 -> 46139 | D3: 1339.89 | E3: 34 | F3: 49 | G3: =IF(E3=0,0,D3/E3) -> 39.408529
A4: 46145 | B4: =TEXT(A4,"dddd") -> Sunday | C4: =A4-WEEKDAY(A4,2)+1 -> 46139 | D4: 1370.72 | E4: 30 | F4: 45 | G4: =IF(E4=0,0,D4/E4) -> 45.690667
A5: 46146 | B5: =TEXT(A5,"dddd") -> Monday | C5: =A5-WEEKDAY(A5,2)+1 -> 46146 | D5: 811.57 | E5: 19 | F5: 31 | G5: =IF(E5=0,0,D5/E5) -> 42.714211
A6: 46147 | B6: =TEXT(A6,"dddd") -> Tuesday | C6: =A6-WEEKDAY(A6,2)+1 -> 46146 | D6: 717.12 | E6: 19 | F6: 30 | G6: =IF(E6=0,0,D6/E6) -> 37.743158
A7: 46148 | B7: =TEXT(A7,"dddd") -> Wednesday | C7: =A7-WEEKDAY(A7,2)+1 -> 46146 | D7: 798.5 | E7: 22 | F7: 33 | G7: =IF(E7=0,0,D7/E7) -> 36.295455
A8: 46149 | B8: =TEXT(A8,"dddd") -> Thursday | C8: =A8-WEEKDAY(A8,2)+1 -> 46146 | D8: 583.79 | E8: 16 | F8: 21 | G8: =IF(E8=0,0,D8/E8) -> 36.486875
A9: 46150 | B9: =TEXT(A9,"dddd") -> Friday | C9: =A9-WEEKDAY(A9,2)+1 -> 46146 | D9: 1170.05 | E9: 32 | F9: 52 | G9: =IF(E9=0,0,D9/E9) -> 36.564062
A10: 46151 | B10: =TEXT(A10,"dddd") -> Saturday | C10: =A10-WEEKDAY(A10,2)+1 -> 46146 | D10: 1492.79 | E10: 37 | F10: 45 | G10: =IF(E10=0,0,D10/E10) -> 40.345676
A11: 46152 | B11: =TEXT(A11,"dddd") -> Sunday | C11: =A11-WEEKDAY(A11,2)+1 -> 46146 | D11: 1143.25 | E11: 28 | F11: 45 | G11: =IF(E11=0,0,D11/E11) -> 40.830357
A12: 46153 | B12: =TEXT(A12,"dddd") -> Monday | C12: =A12-WEEKDAY(A12,2)+1 -> 46153 | D12: 629.25 | E12: 16 | F12: 23 | G12: =IF(E12=0,0,D12/E12) -> 39.328125
A13: 46154 | B13: =TEXT(A13,"dddd") -> Tuesday | C13: =A13-WEEKDAY(A13,2)+1 -> 46153 | D13: 715.41 | E13: 16 | F13: 23 | G13: =IF(E13=0,0,D13/E13) -> 44.713125
... A161: 46302 | B161: =TEXT(A161,"dddd") -> Wednesday | C161: =A161-WEEKDAY(A161,2)+1 -> 46300 | D161: 522.66 | E161: 11 | F161: 17 | G161: =IF(E161=0,0,D161/E161) -> 47.514545

Sheet Weekly
A1: Week start (Mon) | B1: Net sales ($) | C1: Orders | D1: Guests | E1: Avg check ($) | F1: Spend / guest ($) | G1: 4-week avg net sales ($)
A2: 46146 | B2: =SUMIFS(Daily!$D$2:$D$161,Daily!$C$2:$C$161,A2) -> 6717.07 | C2: =SUMIFS(Daily!$E$2:$E$161,Daily!$C$2:$C$161,A2) -> 173 | D2: =SUMIFS(Daily!$F$2:$F$161,Daily!$C$2:$C$161,A2) -> 257 | E2: =IF(C2=0,0,B2/C2) -> 38.826994 | F2: =IF(D2=0,0,B2/D2) -> 26.136459
A3: 46153 | B3: =SUMIFS(Daily!$D$2:$D$161,Daily!$C$2:$C$161,A3) -> 7000.61 | C3: =SUMIFS(Daily!$E$2:$E$161,Daily!$C$2:$C$161,A3) -> 161 | D3: =SUMIFS(Daily!$F$2:$F$161,Daily!$C$2:$C$161,A3) -> 258 | E3: =IF(C3=0,0,B3/C3) -> 43.48205 | F3: =IF(D3=0,0,B3/D3) -> 27.134147
A4: 46160 | B4: =SUMIFS(Daily!$D$2:$D$161,Daily!$C$2:$C$161,A4) -> 7415.2 | C4: =SUMIFS(Daily!$E$2:$E$161,Daily!$C$2:$C$161,A4) -> 174 | D4: =SUMIFS(Daily!$F$2:$F$161,Daily!$C$2:$C$161,A4) -> 257 | E4: =IF(C4=0,0,B4/C4) -> 42.616092 | F4: =IF(D4=0,0,B4/D4) -> 28.852918
A5: 46167 | B5: =SUMIFS(Daily!$D$2:$D$161,Daily!$C$2:$C$161,A5) -> 7398.62 | C5: =SUMIFS(Daily!$E$2:$E$161,Daily!$C$2:$C$161,A5) -> 176 | D5: =SUMIFS(Daily!$F$2:$F$161,Daily!$C$2:$C$161,A5) -> 281 | E5: =IF(C5=0,0,B5/C5) -> 42.037614 | F5: =IF(D5=0,0,B5/D5) -> 26.329609 | G5: =AVERAGE(B2:B5) -> 7132.875
A6: 46174 | B6: =SUMIFS(Daily!$D$2:$D$161,Daily!$C$2:$C$161,A6) -> 7112.94 | C6: =SUMIFS(Daily!$E$2:$E$161,Daily!$C$2:$C$161,A6) -> 172 | D6: =SUMIFS(Daily!$F$2:$F$161,Daily!$C$2:$C$161,A6) -> 272 | E6: =IF(C6=0,0,B6/C6) -> 41.354302 | F6: =IF(D6=0,0,B6/D6) -> 26.150515 | G6: =AVERAGE(B3:B6) -> 7231.8425
A7: 46181 | B7: =SUMIFS(Daily!$D$2:$D$161,Daily!$C$2:$C$161,A7) -> 6560.47 | C7: =SUMIFS(Daily!$E$2:$E$161,Daily!$C$2:$C$161,A7) -> 168 | D7: =SUMIFS(Daily!$F$2:$F$161,Daily!$C$2:$C$161,A7) -> 270 | E7: =IF(C7=0,0,B7/C7) -> 39.050417 | F7: =IF(D7=0,0,B7/D7) -> 24.298037 | G7: =AVERAGE(B4:B7) -> 7121.8075
A8: 46188 | B8: =SUMIFS(Daily!$D$2:$D$161,Daily!$C$2:$C$161,A8) -> 7127.05 | C8: =SUMIFS(Daily!$E$2:$E$161,Daily!$C$2:$C$161,A8) -> 177 | D8: =SUMIFS(Daily!$F$2:$F$161,Daily!$C$2:$C$161,A8) -> 278 | E8: =IF(C8=0,0,B8/C8) -> 40.265819 | F8: =IF(D8=0,0,B8/D8) -> 25.636871 | G8: =AVERAGE(B5:B8) -> 7049.77
A9: 46195 | B9: =SUMIFS(Daily!$D$2:$D$161,Daily!$C$2:$C$161,A9) -> 6527.98 | C9: =SUMIFS(Daily!$E$2:$E$161,Daily!$C$2:$C$161,A9) -> 172 | D9: =SUMIFS(Daily!$F$2:$F$161,Daily!$C$2:$C$161,A9) -> 278 | E9: =IF(C9=0,0,B9/C9) -> 37.953372 | F9: =IF(D9=0,0,B9/D9) -> 23.481942 | G9: =AVERAGE(B6:B9) -> 6832.11
A10: 46202 | B10: =SUMIFS(Daily!$D$2:$D$161,Daily!$C$2:$C$161,A10) -> 7424.59 | C10: =SUMIFS(Daily!$E$2:$E$161,Daily!$C$2:$C$161,A10) -> 182 | D10: =SUMIFS(Daily!$F$2:$F$161,Daily!$C$2:$C$161,A10) -> 303 | E10: =IF(C10=0,0,B10/C10) -> 40.794451 | F10: =IF(D10=0,0,B10/D10) -> 24.503597 | G10: =AVERAGE(B7:B10) -> 6910.0225
A11: 46209 | B11: =SUMIFS(Daily!$D$2:$D$161,Daily!$C$2:$C$161,A11) -> 7489.88 | C11: =SUMIFS(Daily!$E$2:$E$161,Daily!$C$2:$C$161,A11) -> 172 | D11: =SUMIFS(Daily!$F$2:$F$161,Daily!$C$2:$C$161,A11) -> 253 | E11: =IF(C11=0,0,B11/C11) -> 43.545814 | F11: =IF(D11=0,0,B11/D11) -> 29.604269 | G11: =AVERAGE(B8:B11) -> 7142.375
A12: 46216 | B12: =SUMIFS(Daily!$D$2:$D$161,Daily!$C$2:$C$161,A12) -> 6762.14 | C12: =SUMIFS(Daily!$E$2:$E$161,Daily!$C$2:$C$161,A12) -> 172 | D12: =SUMIFS(Daily!$F$2:$F$161,Daily!$C$2:$C$161,A12) -> 269 | E12: =IF(C12=0,0,B12/C12) -> 39.314767 | F12: =IF(D12=0,0,B12/D12) -> 25.138067 | G12: =AVERAGE(B9:B12) -> 7051.1475
A13: 46223 | B13: =SUMIFS(Daily!$D$2:$D$161,Daily!$C$2:$C$161,A13) -> 6970.71 | C13: =SUMIFS(Daily!$E$2:$E$161,Daily!$C$2:$C$161,A13) -> 174 | D13: =SUMIFS(Daily!$F$2:$F$161,Daily!$C$2:$C$161,A13) -> 270 | E13: =IF(C13=0,0,B13/C13) -> 40.061552 | F13: =IF(D13=0,0,B13/D13) -> 25.817444 | G13: =AVERAGE(B10:B13) -> 7161.83
A14: 46230 | B14: =SUMIFS(Daily!$D$2:$D$161,Daily!$C$2:$C$161,A14) -> 7098.45 | C14: =SUMIFS(Daily!$E$2:$E$161,Daily!$C$2:$C$161,A14) -> 186 | D14: =SUMIFS(Daily!$F$2:$F$161,Daily!$C$2:$C$161,A14) -> 300 | E14: =IF(C14=0,0,B14/C14) -> 38.16371 | F14: =IF(D14=0,0,B14/D14) -> 23.6615 | G14: =AVERAGE(B11:B14) -> 7080.295
A15: 46237 | B15: =SUMIFS(Daily!$D$2:$D$161,Daily!$C$2:$C$161,A15) -> 7853.32 | C15: =SUMIFS(Daily!$E$2:$E$161,Daily!$C$2:$C$161,A15) -> 189 | D15: =SUMIFS(Daily!$F$2:$F$161,Daily!$C$2:$C$161,A15) -> 307 | E15: =IF(C15=0,0,B15/C15) -> 41.551958 | F15: =IF(D15=0,0,B15/D15) -> 25.580847 | G15: =AVERAGE(B12:B15) -> 7171.155
A16: 46244 | B16: =SUMIFS(Daily!$D$2:$D$161,Daily!$C$2:$C$161,A16) -> 7122.53 | C16: =SUMIFS(Daily!$E$2:$E$161,Daily!$C$2:$C$161,A16) -> 173 | D16: =SUMIFS(Daily!$F$2:$F$161,Daily!$C$2:$C$161,A16) -> 271 | E16: =IF(C16=0,0,B16/C16) -> 41.170694 | F16: =IF(D16=0,0,B16/D16) -> 26.282399 | G16: =AVERAGE(B13:B16) -> 7261.2525
... A23: 46293 | B23: =SUMIFS(Daily!$D$2:$D$161,Daily!$C$2:$C$161,A23) -> 5844.54 | C23: =SUMIFS(Daily!$E$2:$E$161,Daily!$C$2:$C$161,A23) -> 145 | D23: =SUMIFS(Daily!$F$2:$F$161,Daily!$C$2:$C$161,A23) -> 224 | E23: =IF(C23=0,0,B23/C23) -> 40.307172 | F23: =IF(D23=0,0,B23/D23) -> 26.091696 | G23: =AVERAGE(B20:B23) -> 6214.1525

Sheet Decomposition
A1: Why did sales fall? Net sales = Orders x Average check
A3: Weekly average | B3: Base period | C3: Recent period | D3: Change | E3: % change
A4: Net sales ($ / week) | B4: =AVERAGEIFS(Weekly!$B$2:$B$23,Weekly!$A$2:$A$23,">="&Assumptions!$B$4,Weekly!$A$2:$A$23,"<="&Assumptions!$B$5) -> 7143.7588 | C4: =AVERAGEIFS(Weekly!$B$2:$B$23,Weekly!$A$2:$A$23,">="&Assumptions!$B$6,Weekly!$A$2:$A$23,"<="&Assumptions!$B$7) -> 6214.1525 | D4: =C4-B4 -> -929.60632 | E4: =IF(B4=0,0,D4/B4) -> -0.13012846
A5: Orders / week | B5: =AVERAGEIFS(Weekly!$C$2:$C$23,Weekly!$A$2:$A$23,">="&Assumptions!$B$4,Weekly!$A$2:$A$23,"<="&Assumptions!$B$5) -> 175.64706 | C5: =AVERAGEIFS(Weekly!$C$2:$C$23,Weekly!$A$2:$A$23,">="&Assumptions!$B$6,Weekly!$A$2:$A$23,"<="&Assumptions!$B$7) -> 154.75 | D5: =C5-B5 -> -20.897059 | E5: =IF(B5=0,0,D5/B5) -> -0.11897187
A6: Guests / week | B6: =AVERAGEIFS(Weekly!$D$2:$D$23,Weekly!$A$2:$A$23,">="&Assumptions!$B$4,Weekly!$A$2:$A$23,"<="&Assumptions!$B$5) -> 277.05882 | C6: =AVERAGEIFS(Weekly!$D$2:$D$23,Weekly!$A$2:$A$23,">="&Assumptions!$B$6,Weekly!$A$2:$A$23,"<="&Assumptions!$B$7) -> 244.25 | D6: =C6-B6 -> -32.808824 | E6: =IF(B6=0,0,D6/B6) -> -0.11841826
A7: Average check ($) = net sales / orders | B7: =B4/B5 -> 40.671098 | C7: =C4/C5 -> 40.156074 | D7: =C7-B7 -> -0.51502415 | E7: =IF(B7=0,0,D7/B7) -> -0.012663148
A9: Where did the drop come from? (sums exactly to the total change)
A10: Traffic effect = (recent orders - base orders) x base avg check | B10: =(C5-B5)*B7 -> -849.90634
A11: Average-check effect = recent orders x (recent avg check - base avg check) | B11: =C5*(C7-B7) -> -79.699987
A12: Total change in weekly net sales | B12: =B10+B11 -> -929.60632
A13: Check: equals change in net sales row above | B13: =IF(ABS(B12-D4)<0.01,"OK","MISMATCH") -> OK
A14: Traffic effect as % of total change | B14: =IF(B12=0,0,B10/B12) -> 0.9142648
A17: Average net sales by day of week
A18: Day | B18: Base ($/day) | C18: Recent ($/day) | D18: Change ($/day) | E18: % change
A19: Monday | B19: =AVERAGEIFS(Daily!$D$2:$D$161,Daily!$B$2:$B$161,A19,Daily!$A$2:$A$161,">="&Assumptions!$B$4,Daily!$A$2:$A$161,"<="&Assumptions!$B$8) -> 790.99824 | C19: =AVERAGEIFS(Daily!$D$2:$D$161,Daily!$B$2:$B$161,A19,Daily!$A$2:$A$161,">="&Assumptions!$B$6,Daily!$A$2:$A$161,"<="&Assumptions!$B$9) -> 721.1825 | D19: =C19-B19 -> -69.815735 | E19: =IF(B19=0,0,D19/B19) -> -0.088262821
A20: Tuesday | B20: =AVERAGEIFS(Daily!$D$2:$D$161,Daily!$B$2:$B$161,A20,Daily!$A$2:$A$161,">="&Assumptions!$B$4,Daily!$A$2:$A$161,"<="&Assumptions!$B$8) -> 726.46765 | C20: =AVERAGEIFS(Daily!$D$2:$D$161,Daily!$B$2:$B$161,A20,Daily!$A$2:$A$161,">="&Assumptions!$B$6,Daily!$A$2:$A$161,"<="&Assumptions!$B$9) -> 553.7225 | D20: =C20-B20 -> -172.74515 | E20: =IF(B20=0,0,D20/B20) -> -0.2377878
A21: Wednesday | B21: =AVERAGEIFS(Daily!$D$2:$D$161,Daily!$B$2:$B$161,A21,Daily!$A$2:$A$161,">="&Assumptions!$B$4,Daily!$A$2:$A$161,"<="&Assumptions!$B$8) -> 793.93647 | C21: =AVERAGEIFS(Daily!$D$2:$D$161,Daily!$B$2:$B$161,A21,Daily!$A$2:$A$161,">="&Assumptions!$B$6,Daily!$A$2:$A$161,"<="&Assumptions!$B$9) -> 612.3575 | D21: =C21-B21 -> -181.57897 | E21: =IF(B21=0,0,D21/B21) -> -0.22870718
A22: Thursday | B22: =AVERAGEIFS(Daily!$D$2:$D$161,Daily!$B$2:$B$161,A22,Daily!$A$2:$A$161,">="&Assumptions!$B$4,Daily!$A$2:$A$161,"<="&Assumptions!$B$8) -> 807.85294 | C22: =AVERAGEIFS(Daily!$D$2:$D$161,Daily!$B$2:$B$161,A22,Daily!$A$2:$A$161,">="&Assumptions!$B$6,Daily!$A$2:$A$161,"<="&Assumptions!$B$9) -> 672.0925 | D22: =C22-B22 -> -135.76044 | E22: =IF(B22=0,0,D22/B22) -> -0.16805093
A23: Friday | B23: =AVERAGEIFS(Daily!$D$2:$D$161,Daily!$B$2:$B$161,A23,Daily!$A$2:$A$161,">="&Assumptions!$B$4,Daily!$A$2:$A$161,"<="&Assumptions!$B$8) -> 1291.1665 | C23: =AVERAGEIFS(Daily!$D$2:$D$161,Daily!$B$2:$B$161,A23,Daily!$A$2:$A$161,">="&Assumptions!$B$6,Daily!$A$2:$A$161,"<="&Assumptions!$B$9) -> 1207.345 | D23: =C23-B23 -> -83.821471 | E23: =IF(B23=0,0,D23/B23) -> -0.064919182
A24: Saturday | B24: =AVERAGEIFS(Daily!$D$2:$D$161,Daily!$B$2:$B$161,A24,Daily!$A$2:$A$161,">="&Assumptions!$B$4,Daily!$A$2:$A$161,"<="&Assumptions!$B$8) -> 1506.6618 | C24: =AVERAGEIFS(Daily!$D$2:$D$161,Daily!$B$2:$B$161,A24,Daily!$A$2:$A$161,">="&Assumptions!$B$6,Daily!$A$2:$A$161,"<="&Assumptions!$B$9) -> 1476.2825 | D24: =C24-B24 -> -30.379265 | E24: =IF(B24=0,0,D24/B24) -> -0.020163294
A25: Sunday | B25: =AVERAGEIFS(Daily!$D$2:$D$161,Daily!$B$2:$B$161,A25,Daily!$A$2:$A$161,">="&Assumptions!$B$4,Daily!$A$2:$A$161,"<="&Assumptions!$B$8) -> 1226.6753 | C25: =AVERAGEIFS(Daily!$D$2:$D$161,Daily!$B$2:$B$161,A25,Daily!$A$2:$A$161,">="&Assumptions!$B$6,Daily!$A$2:$A$161,"<="&Assumptions!$B$9) -> 971.17 | D25: =C25-B25 -> -255.50529 | E25: =IF(B25=0,0,D25/B25) -> -0.20829089
A26: Total per week | B26: =SUM(B19:B25) -> 7143.7588 | C26: =SUM(C19:C25) -> 6214.1525 | D26: =SUM(D19:D25) -> -929.60632 | E26: =IF(B26=0,0,D26/B26) -> -0.13012846

Sheet Scenario
A1: Illustrative scenario: win back some weeknight sales
A3: Weekly sales gap on days that fell (Mon-Thu + Sun), $ / week | B3: =-SUMIF(Decomposition!D19:D25,"<0") -> 929.60632
A4: Share of that gap recovered (from Assumptions) | B4: =Assumptions!B18 -> 0.25
A5: Added net sales per week | B5: =B3*B4 -> 232.40158
A6: Added gross profit per week (net of placeholder food cost) | B6: =B5*(1-Assumptions!B12) -> 162.68111 | C6: Depends on PLACEHOLDER food cost %.
A7: Added gross profit per 13 weeks (one quarter) | B7: =B6*13 -> 2114.8544 | C7: Quarter, not annualized: seasonality is unknown without prior-year data.

Sheet Monthly P&L (est)
A1: Estimated monthly operating profit - USES PLACEHOLDER COST INPUTS
A3: Month | B3: Start | C3: End | D3: Days | E3: Net sales ($) | F3: Net sales / day ($) | G3: Food cost ($) | H3: Labor ($) | I3: Other opex ($) | J3: Rent & fixed ($) | K3: Est. operating profit ($) | L3: Margin
A4: May | B4: 46143 | C4: 46173 | D4: =C4-B4+1 -> 31 | E4: =SUMIFS(Daily!$D$2:$D$161,Daily!$A$2:$A$161,">="&B4,Daily!$A$2:$A$161,"<="&C4) -> 32629.62 | F4: =E4/D4 -> 1052.5684 | G4: =E4*Assumptions!$B$12 -> 9788.886 | H4: =E4*Assumptions!$B$13 -> 9788.886 | I4: =E4*Assumptions!$B$14 -> 3262.962 | J4: =Assumptions!$B$15*D4/DAY(EOMONTH(B4,0)) -> 8000 | K4: =E4-G4-H4-I4-J4 -> 1788.886 | L4: =IF(E4=0,0,K4/E4) -> 0.054823991
A5: June | B5: 46174 | C5: 46203 | D5: =C5-B5+1 -> 30 | E5: =SUMIFS(Daily!$D$2:$D$161,Daily!$A$2:$A$161,">="&B5,Daily!$A$2:$A$161,"<="&C5) -> 28793.62 | F5: =E5/D5 -> 959.78733 | G5: =E5*Assumptions!$B$12 -> 8638.086 | H5: =E5*Assumptions!$B$13 -> 8638.086 | I5: =E5*Assumptions!$B$14 -> 2879.362 | J5: =Assumptions!$B$15*D5/DAY(EOMONTH(B5,0)) -> 8000 | K5: =E5-G5-H5-I5-J5 -> 638.086 | L5: =IF(E5=0,0,K5/E5) -> 0.022160673
A6: July | B6: 46204 | C6: 46234 | D6: =C6-B6+1 -> 31 | E6: =SUMIFS(Daily!$D$2:$D$161,Daily!$A$2:$A$161,">="&B6,Daily!$A$2:$A$161,"<="&C6) -> 31872.74 | F6: =E6/D6 -> 1028.1529 | G6: =E6*Assumptions!$B$12 -> 9561.822 | H6: =E6*Assumptions!$B$13 -> 9561.822 | I6: =E6*Assumptions!$B$14 -> 3187.274 | J6: =Assumptions!$B$15*D6/DAY(EOMONTH(B6,0)) -> 8000 | K6: =E6-G6-H6-I6-J6 -> 1561.822 | L6: =IF(E6=0,0,K6/E6) -> 0.049001812
A7: August | B7: 46235 | C7: 46265 | D7: =C7-B7+1 -> 31 | E7: =SUMIFS(Daily!$D$2:$D$161,Daily!$A$2:$A$161,">="&B7,Daily!$A$2:$A$161,"<="&C7) -> 32787.07 | F7: =E7/D7 -> 1057.6474 | G7: =E7*Assumptions!$B$12 -> 9836.121 | H7: =E7*Assumptions!$B$13 -> 9836.121 | I7: =E7*Assumptions!$B$14 -> 3278.707 | J7: =Assumptions!$B$15*D7/DAY(EOMONTH(B7,0)) -> 8000 | K7: =E7-G7-H7-I7-J7 -> 1836.121 | L7: =IF(E7=0,0,K7/E7) -> 0.056001375
A8: September | B8: 46266 | C8: 46295 | D8: =C8-B8+1 -> 30 | E8: =SUMIFS(Daily!$D$2:$D$161,Daily!$A$2:$A$161,">="&B8,Daily!$A$2:$A$161,"<="&C8) -> 27274.49 | F8: =E8/D8 -> 909.14967 | G8: =E8*Assumptions!$B$12 -> 8182.347 | H8: =E8*Assumptions!$B$13 -> 8182.347 | I8: =E8*Assumptions!$B$14 -> 2727.449 | J8: =Assumptions!$B$15*D8/DAY(EOMONTH(B8,0)) -> 8000 | K8: =E8-G8-H8-I8-J8 -> 182.347 | L8: =IF(E8=0,0,K8/E8) -> 0.0066856246
A9: Oct 1-7 (partial) | B9: 46296 | C9: 46302 | D9: =C9-B9+1 -> 7 | E9: =SUMIFS(Daily!$D$2:$D$161,Daily!$A$2:$A$161,">="&B9,Daily!$A$2:$A$161,"<="&C9) -> 5677.84 | F9: =E9/D9 -> 811.12 | G9: =E9*Assumptions!$B$12 -> 1703.352 | H9: =E9*Assumptions!$B$13 -> 1703.352 | I9: =E9*Assumptions!$B$14 -> 567.784 | J9: =Assumptions!$B$15*D9/DAY(EOMONTH(B9,0)) -> 1806.4516 | K9: =E9-G9-H9-I9-J9 -> -103.09961 | L9: =IF(E9=0,0,K9/E9) -> -0.018158246
A11: Rent is prorated by days in the month. Every cost line is a % of sales or a flat placeholder - replace Assumptions B12:B15 with real figures before relying on any profit number.
